{"obj_edit_time":"1742716989","blocks":[{"block_id":"RhjxdgG6oo5XOixfOPycU1iLnmc","block_type":1,"children":["ECWUdcbaNoIfAtxe0z2cb9h2nKd","Hfr4dEE4Uo847HxrlRmcXwZbnGh","FHJydGUw8oJgBfxq1Rkcmsm9nUd","OYh0doURBondfbxq2wZc9DFbnTd","ViCWdpopNooaToxpM89ctvorn0g","V5JJdVavroBxxExmjtdcuCG2n2d","D4YOdyifjompn6xOGercMzZHnFd","LsL3dS7S9ogMOkxE8h1c9Ywnnrb","SHYRdMS1EoUugKxIs8Ic7wScnDb","Nm4LdGrkaoGMcXxK3uccSX2EnKg","K5tEdhKQSogbw5x5SmTco9vwnzd","OfHTdo1zXokMnExMGiGcNrBhnfc","VaSHdcpTLoURb5xb5Ljc9lgknvb","TGP6dbaCXojw0RxrnrkcFdDJnTh","FGe1djk9FoTqpQxnAOYccmrtnxg","QL7wdXQBQo4Yfbx7ZQoc10mFnBd","KsC6d0ofyoYwL1xNdVccYL7snJe","HoWrdJKzYoVXEgxmrInc1WsinCh","TSPmdelV7oxWshx96hXc3ScJnLe","UDgOdrHDyoqTukxcmzrc7fP5n0d"],"page":{"elements":[{"text_run":{"content":"常见问题C1","text_element_style":{"bold":false,"inline_code":false,"italic":false,"strikethrough":false,"underline":false}}}],"style":{"align":1}},"parent_id":""},{"block_id":"ECWUdcbaNoIfAtxe0z2cb9h2nKd","block_type":50,"parent_id":"RhjxdgG6oo5XOixfOPycU1iLnmc","reference_synced":{"source_block_id":"Df8RdoFfys17kPb8qkNc7DnDnxc","source_document_id":"V3fHdvfwIoScWWxqvo4ctMv7nUE"}},{"block_id":"Hfr4dEE4Uo847HxrlRmcXwZbnGh","block_type":3,"heading1":{"elements":[{"text_run":{"content":"怎么模仿人类输出（分段输出）？","text_element_style":{"bold":false,"inline_code":false,"italic":false,"strikethrough":false,"underline":false}}}],"style":{"align":1,"folded":false}},"parent_id":"RhjxdgG6oo5XOixfOPycU1iLnmc"},{"block_id":"FHJydGUw8oJgBfxq1Rkcmsm9nUd","block_type":2,"parent_id":"RhjxdgG6oo5XOixfOPycU1iLnmc","text":{"elements":[{"text_run":{"content":"效果：","text_element_style":{"bold":false,"inline_code":false,"italic":false,"strikethrough":false,"underline":false}}}],"style":{"align":1,"folded":false}}},{"block_id":"OYh0doURBondfbxq2wZc9DFbnTd","block_type":2,"parent_id":"RhjxdgG6oo5XOixfOPycU1iLnmc","text":{"elements":[{"text_run":{"content":"让AI回复的更像人类","text_element_style":{"bold":false,"inline_code":false,"italic":false,"strikethrough":false,"underline":false}}}],"style":{"align":1,"folded":false}}},{"block_id":"ViCWdpopNooaToxpM89ctvorn0g","block_type":27,"image":{"align":2,"height":539,"token":"GMyMbbYlHovtMdxL6UxcLBMNn7b","width":435},"parent_id":"RhjxdgG6oo5XOixfOPycU1iLnmc"},{"block_id":"V5JJdVavroBxxExmjtdcuCG2n2d","block_type":2,"parent_id":"RhjxdgG6oo5XOixfOPycU1iLnmc","text":{"elements":[{"text_run":{"content":"教程：","text_element_style":{"bold":false,"inline_code":false,"italic":false,"strikethrough":false,"underline":false}}}],"style":{"align":1,"folded":false}}},{"block_id":"D4YOdyifjompn6xOGercMzZHnFd","block_type":2,"parent_id":"RhjxdgG6oo5XOixfOPycU1iLnmc","text":{"elements":[{"text_run":{"content":"工作流：","text_element_style":{"bold":false,"inline_code":false,"italic":false,"strikethrough":false,"underline":false}}}],"style":{"align":1,"folded":false}}},{"block_id":"LsL3dS7S9ogMOkxE8h1c9Ywnnrb","block_type":27,"image":{"align":2,"height":633,"token":"QZ2mbJWOgo6Y7gx3Iu6cKTpTnob","width":1084},"parent_id":"RhjxdgG6oo5XOixfOPycU1iLnmc"},{"block_id":"SHYRdMS1EoUugKxIs8Ic7wScnDb","block_type":2,"parent_id":"RhjxdgG6oo5XOixfOPycU1iLnmc","text":{"elements":[{"text_run":{"content":"假设大模型节点就是需要的回复，并且已经按句号（。）区别开每句话","text_element_style":{"bold":false,"inline_code":false,"italic":false,"strikethrough":false,"underline":false}}}],"style":{"align":1,"folded":false}}},{"block_id":"Nm4LdGrkaoGMcXxK3uccSX2EnKg","block_type":2,"parent_id":"RhjxdgG6oo5XOixfOPycU1iLnmc","text":{"elements":[{"text_run":{"content":"后面连接一个 文本处理 节点，选择“字符串分隔”，按“。”进行分割","text_element_style":{"bold":false,"inline_code":false,"italic":false,"strikethrough":false,"underline":false}}}],"style":{"align":1,"folded":false}}},{"block_id":"K5tEdhKQSogbw5x5SmTco9vwnzd","block_type":27,"image":{"align":2,"height":646,"token":"TJs6bzsj9oeh0axRn6scNv8UnBd","width":1114},"parent_id":"RhjxdgG6oo5XOixfOPycU1iLnmc"},{"block_id":"OfHTdo1zXokMnExMGiGcNrBhnfc","block_type":2,"parent_id":"RhjxdgG6oo5XOixfOPycU1iLnmc","text":{"elements":[{"text_run":{"content":"分割后是一个数组，里面存储的是每句话。","text_element_style":{"bold":false,"inline_code":false,"italic":false,"strikethrough":false,"underline":false}}}],"style":{"align":1,"folded":false}}},{"block_id":"VaSHdcpTLoURb5xb5Ljc9lgknvb","block_type":2,"parent_id":"RhjxdgG6oo5XOixfOPycU1iLnmc","text":{"elements":[{"text_run":{"content":"这一步其实可以直接让大模型输出，修改大模型节点的参数就好。","text_element_style":{"bold":false,"inline_code":false,"italic":false,"strikethrough":false,"underline":false}}}],"style":{"align":1,"folded":false}}},{"block_id":"TGP6dbaCXojw0RxrnrkcFdDJnTh","block_type":2,"parent_id":"RhjxdgG6oo5XOixfOPycU1iLnmc","text":{"elements":[{"text_run":{"content":"后面咱们再接一个 循环 节点，把每句话都输出","text_element_style":{"bold":false,"inline_code":false,"italic":false,"strikethrough":false,"underline":false}}}],"style":{"align":1,"folded":false}}},{"block_id":"FGe1djk9FoTqpQxnAOYccmrtnxg","block_type":27,"image":{"align":2,"height":613,"token":"Vd9Wb1VyIotlPZx8Bymclu2Ln9d","width":1113},"parent_id":"RhjxdgG6oo5XOixfOPycU1iLnmc"},{"block_id":"QL7wdXQBQo4Yfbx7ZQoc10mFnBd","block_type":2,"parent_id":"RhjxdgG6oo5XOixfOPycU1iLnmc","text":{"elements":[{"text_run":{"content":"循环类型选择 “使用数组循环”，循环数组选择 文本处理 节点的返回值，中间变量和输出变量不定义。","text_element_style":{"bold":false,"inline_code":false,"italic":false,"strikethrough":false,"underline":false}}}],"style":{"align":1,"folded":false}}},{"block_id":"KsC6d0ofyoYwL1xNdVccYL7snJe","block_type":2,"parent_id":"RhjxdgG6oo5XOixfOPycU1iLnmc","text":{"elements":[{"text_run":{"content":"循环体里面放一个 输出 节点即可，输出内容选择循环的item变量，也就是需要输出的每句话。","text_element_style":{"bold":false,"inline_code":false,"italic":false,"strikethrough":false,"underline":false}}}],"style":{"align":1,"folded":false}}},{"block_id":"HoWrdJKzYoVXEgxmrInc1WsinCh","block_type":24,"children":["QryxdXuacoclrCx4POOc8Q2BnXg","Usqbd9bg7oWf3OxHMHEcuY3RnWd"],"grid":{"column_size":2},"parent_id":"RhjxdgG6oo5XOixfOPycU1iLnmc"},{"block_id":"QryxdXuacoclrCx4POOc8Q2BnXg","block_type":25,"children":["NOZ2du9x9oFCBExU69mcCuaKn9c","ShYtdWKKJo71OHx75lscZR5XnWh"],"grid_column":{"width_ratio":50},"parent_id":"HoWrdJKzYoVXEgxmrInc1WsinCh"},{"block_id":"NOZ2du9x9oFCBExU69mcCuaKn9c","block_type":27,"image":{"align":2,"height":376,"token":"MMs5b3ZvdouYK8xLmkgcSHDInOc","width":614},"parent_id":"QryxdXuacoclrCx4POOc8Q2BnXg"},{"block_id":"ShYtdWKKJo71OHx75lscZR5XnWh","block_type":2,"parent_id":"QryxdXuacoclrCx4POOc8Q2BnXg","text":{"elements":[{"text_run":{"content":"","text_element_style":{"bold":false,"inline_code":false,"italic":false,"strikethrough":false,"underline":false}}}],"style":{"align":1,"folded":false}}},{"block_id":"Usqbd9bg7oWf3OxHMHEcuY3RnWd","block_type":25,"children":["ImbFdkUXboKTVpxzZ4gcxlqinbg","V8uSd7EyBoVDMhxKtxOcJcBEnEh"],"grid_column":{"width_ratio":50},"parent_id":"HoWrdJKzYoVXEgxmrInc1WsinCh"},{"block_id":"ImbFdkUXboKTVpxzZ4gcxlqinbg","block_type":27,"image":{"align":2,"height":418,"token":"Eb6gbRy1mol5fBxxS8rcH4xNnk9","width":500},"parent_id":"Usqbd9bg7oWf3OxHMHEcuY3RnWd"},{"block_id":"V8uSd7EyBoVDMhxKtxOcJcBEnEh","block_type":2,"parent_id":"Usqbd9bg7oWf3OxHMHEcuY3RnWd","text":{"elements":[{"text_run":{"content":"","text_element_style":{"bold":false,"inline_code":false,"italic":false,"strikethrough":false,"underline":false}}}],"style":{"align":1,"folded":false}}},{"block_id":"TSPmdelV7oxWshx96hXc3ScJnLe","block_type":22,"divider":{},"parent_id":"RhjxdgG6oo5XOixfOPycU1iLnmc"},{"block_id":"UDgOdrHDyoqTukxcmzrc7fP5n0d","block_type":2,"parent_id":"RhjxdgG6oo5XOixfOPycU1iLnmc","text":{"elements":[{"text_run":{"content":"","text_element_style":{"bold":false,"inline_code":false,"italic":false,"strikethrough":false,"underline":false}}}],"style":{"align":1,"folded":false}}}]}